ost/__init__.py
ost/evaluator_cli.py
ost/metrics.py
ost_python-0.0.9.dist-info/LICENSE
ost_python-0.0.9.dist-info/METADATA
ost_python-0.0.9.dist-info/WHEEL
ost_python-0.0.9.dist-info/entry_points.txt
ost_python-0.0.9.dist-info/top_level.txt
ost_python-0.0.9.dist-info/RECORD
